django_daraja/__init__.py
django_daraja/admin.py
django_daraja/apps.py
django_daraja/models.py
django_daraja/urls.py
django_daraja/views.py
django_daraja/migrations/0001_initial.py
django_daraja/migrations/0002_auto_20181108_1219.py
django_daraja/migrations/__init__.py
django_daraja/mpesa/__init__.py
django_daraja/mpesa/core.py
django_daraja/mpesa/exceptions.py
django_daraja/mpesa/utils.py
django_daraja-1.2.0.dist-info/LICENCE.txt
django_daraja-1.2.0.dist-info/METADATA
django_daraja-1.2.0.dist-info/WHEEL
django_daraja-1.2.0.dist-info/top_level.txt
django_daraja-1.2.0.dist-info/RECORD
